todoist_mcp/__init__.py
todoist_mcp/api_v1.py
todoist_mcp/auth.py
todoist_mcp/server.py
todoist_mcp-0.4.0.dist-info/METADATA
todoist_mcp-0.4.0.dist-info/WHEEL
todoist_mcp-0.4.0.dist-info/entry_points.txt
todoist_mcp-0.4.0.dist-info/top_level.txt
todoist_mcp-0.4.0.dist-info/RECORD
